odoo/addons/web_dialog_size/README.rst
odoo/addons/web_dialog_size/__init__.py
odoo/addons/web_dialog_size/__manifest__.py
odoo/addons/web_dialog_size/i18n/de.po
odoo/addons/web_dialog_size/i18n/es.po
odoo/addons/web_dialog_size/i18n/fr.po
odoo/addons/web_dialog_size/i18n/it.po
odoo/addons/web_dialog_size/i18n/nl.po
odoo/addons/web_dialog_size/i18n/web_dialog_size.pot
odoo/addons/web_dialog_size/i18n/zh_CN.po
odoo/addons/web_dialog_size/models/__init__.py
odoo/addons/web_dialog_size/models/ir_config_parameter.py
odoo/addons/web_dialog_size/readme/CONFIGURATION.rst
odoo/addons/web_dialog_size/readme/CONFIGURE.rst
odoo/addons/web_dialog_size/readme/CONTRIBUTORS.rst
odoo/addons/web_dialog_size/readme/DESCRIPTION.rst
odoo/addons/web_dialog_size/readme/ROADMAP.rst
odoo/addons/web_dialog_size/static/description/icon.png
odoo/addons/web_dialog_size/static/description/index.html
odoo/addons/web_dialog_size/static/src/js/web_dialog_size.js
odoo/addons/web_dialog_size/static/src/scss/web_dialog_size.scss
odoo/addons/web_dialog_size/static/src/xml/web_dialog_size.xml
odoo/addons/web_dialog_size/templates/assets.xml
odoo/addons/web_dialog_size/tests/__init__.py
odoo/addons/web_dialog_size/tests/test_web_dialog_size.py
odoo14_addon_web_dialog_size-14.0.1.0.1.dev20.dist-info/METADATA
odoo14_addon_web_dialog_size-14.0.1.0.1.dev20.dist-info/WHEEL
odoo14_addon_web_dialog_size-14.0.1.0.1.dev20.dist-info/top_level.txt
odoo14_addon_web_dialog_size-14.0.1.0.1.dev20.dist-info/RECORD
