Metadata-Version: 2.1
Name: odoo14-addon-web-dialog-size
Version: 14.0.1.0.1.dev20
Summary: A module that lets the user expand a dialog box to the full screen width.
Home-page: https://github.com/OCA/web
Author: ACSONE SA/NV, Therp BV, Siddharth Bhalgami,Tecnativa, Amaris, Odoo Community Association (OCA)
Author-email: support@odoo-community.org
License: AGPL-3
Platform: UNKNOWN
Classifier: Programming Language :: Python
Classifier: Framework :: Odoo
Classifier: Framework :: Odoo :: 14.0
Classifier: License :: OSI Approved :: GNU Affero General Public License v3
Requires-Python: >=3.6
Requires-Dist: odoo <14.1dev,>=14.0a
